playgent/__init__.py
playgent/core.py
playgent/cost_calculator.py
playgent/decorators.py
playgent/import_hooks.py
playgent/spans.py
playgent/state.py
playgent/types.py
playgent/wrappers.py
playgent-0.1.5.dist-info/licenses/LICENSE
playgent-0.1.5.dist-info/METADATA
playgent-0.1.5.dist-info/WHEEL
playgent-0.1.5.dist-info/top_level.txt
playgent-0.1.5.dist-info/RECORD
