Metadata-Version: 2.4
Name: playgent
Version: 0.1.5
Summary: SDK for tracking and testing OpenAI API calls
Author-email: Aniruddh Sriram <aniruddh.sriram@gmail.com>
Maintainer-email: Aniruddh Sriram <aniruddh.sriram@gmail.com>
License: MIT
Project-URL: Homepage, https://github.com/AniruddhS24/playgent-py
Project-URL: Documentation, https://github.com/AniruddhS24/playgent-py#readme
Project-URL: Repository, https://github.com/AniruddhS24/playgent-py
Project-URL: Issues, https://github.com/AniruddhS24/playgent-py/issues
Project-URL: Changelog, https://github.com/AniruddhS24/playgent-py/releases
Keywords: openai,api,testing,tracking,replay,evaluation,sdk
Classifier: Development Status :: 3 - Alpha
Classifier: Intended Audience :: Developers
Classifier: Operating System :: OS Independent
Classifier: Programming Language :: Python
Classifier: Programming Language :: Python :: 3
Classifier: Programming Language :: Python :: 3.8
Classifier: Programming Language :: Python :: 3.9
Classifier: Programming Language :: Python :: 3.10
Classifier: Programming Language :: Python :: 3.11
Classifier: Programming Language :: Python :: 3.12
Classifier: Topic :: Software Development :: Libraries :: Python Modules
Classifier: Topic :: Software Development :: Testing
Classifier: Topic :: Software Development :: Quality Assurance
Requires-Python: >=3.8
License-File: LICENSE
Requires-Dist: openai>=1.0.0
Requires-Dist: httpx>=0.24.0
Requires-Dist: pydantic>=2.0.0
Requires-Dist: opentelemetry-api>=1.20.0
Requires-Dist: opentelemetry-sdk>=1.20.0
Requires-Dist: python-dotenv>=1.0.1
Provides-Extra: dev
Requires-Dist: pytest>=7.0.0; extra == "dev"
Requires-Dist: pytest-asyncio>=0.21.0; extra == "dev"
Requires-Dist: build>=0.10.0; extra == "dev"
Requires-Dist: twine>=4.0.0; extra == "dev"
Requires-Dist: black>=23.0.0; extra == "dev"
Requires-Dist: ruff>=0.1.0; extra == "dev"
Requires-Dist: mypy>=1.0.0; extra == "dev"
Dynamic: license-file
